quran_suras/__init__.py
quran_suras/quran_suras.py
quran_suras-1.1.4.dist-info/LICENSE
quran_suras-1.1.4.dist-info/METADATA
quran_suras-1.1.4.dist-info/WHEEL
quran_suras-1.1.4.dist-info/top_level.txt
quran_suras-1.1.4.dist-info/RECORD
