Metadata-Version: 2.1
Name: quran-suras
Version: 1.1.4
Summary: API of the mp3quran.net, which helps you to fetch the surahs of the Qur’an via the surah number or name and more
Home-page: https://codeberg.org/Awiteb/quran_suras
Author: Awiteb
Author-email: Awiteb@hotmail.com
License: UNKNOWN
Keywords: surah,sura,quran
Platform: UNKNOWN
Classifier: Programming Language :: Python :: 3.7
Classifier: Programming Language :: Python :: 3.8
Classifier: Programming Language :: Python :: 3.9
Classifier: Programming Language :: Python :: 3.10
Classifier: License :: OSI Approved :: GNU General Public License v3 (GPLv3)
Classifier: Operating System :: OS Independent
Requires-Python: >=3.7
Requires-Dist: certifi (==2021.5.30)
Requires-Dist: chardet (==4.0.0)
Requires-Dist: idna (==2.10)
Requires-Dist: requests (==2.25.1)
Requires-Dist: urllib3 (==1.26.5)
